{
    "version": "5",
    "advisor": "David Brown",
    "client": "Edward",
    "conversations": [
        {
            "conversation_id": "conv_0049",
            "timestamp": "2025-03-19T03:32:01.314709Z",
            "category": "Deal negotiations",
            "topic": "Deal negotiations",
            "lines": [
                {
                    "speaker": "1",
                    "text": "Morning Edward!  The overall market's a bit jittery, but there are some interesting pockets of strength.  We're seeing a lot of activity in the real estate sector, particularly with REITs.  Covivio (COV.PA) has been on my radar lately; their recent portfolio adjustments seem promising, though the overall market sentiment is impacting their valuation.  What are your initial thoughts on the current market dynamics, and specifically, any interest in the current Covivio situation?"
                },
                {
                    "speaker": "0",
                    "text": "Thanks David.  Covivio is definitely on our watchlist."
                },
                {
                    "speaker": "1",
                    "text": "Their Q2 earnings were slightly below expectations, but their long-term strategy seems sound.  They're focusing on sustainable development and prime locations, which should pay off in the long run.  However, the current interest rate environment is a significant headwind for the entire sector, impacting valuations across the board.  We're projecting a moderate growth for Covivio in the next few quarters, but it's heavily dependent on macroeconomic factors."
                },
                {
                    "speaker": "0",
                    "text": "Interesting. How does that compare to your projections for other major players in the French REIT market?  Are there any comparable companies showing stronger potential for growth, considering the current economic climate?"
                },
                {
                    "speaker": "1",
                    "text": "Good question.  It's tough to find a direct comparison with Covivio's specific portfolio.  But overall, the sector is facing similar challenges."
                }
            ],
            "key_companies": [
                {
                    "extracted_entity": "Covivio",
                    "official_name": "Covivio",
                    "ticker": "COV.PA"
                }
            ]
        },
        {
            "conversation_id": "conv_0067",
            "timestamp": "2025-03-19T03:32:01.381301Z",
            "category": "Earnings reports discussions",
            "topic": "Earnings reports discussions",
            "lines": [
                {
                    "speaker": "1",
                    "text": "Good morning, Edward.  The overall market sentiment seems cautiously optimistic this week, driven primarily by positive tech earnings and some stabilization in the energy sector.  However, there's still considerable uncertainty surrounding inflation and interest rate hikes."
                },
                {
                    "speaker": "0",
                    "text": "Thanks, David. I'm particularly interested in your assessment of Grab Holdings (GRAB) and Sons of Gwalia's recent performance.  Grab's earnings were a bit mixed, with strong growth in some segments offset by losses in others.  Their guidance also seemed somewhat conservative.  Meanwhile, I'm struggling to find much concrete information on Sons of Gwalia's recent financial activity, given the lack of readily available public data.  Could you shed some light on your interpretation of both companies' performance and outlook, considering their respective market positions and future growth potential?  I'm keen to understand how you're factoring these results into your portfolio strategy, especially in light of the broader macroeconomic environment."
                },
                {
                    "speaker": "1",
                    "text": "Regarding Grab, I agree their results were mixed.  The key is to analyze the underlying drivers of their growth and losses.  Their expansion into new markets is promising, but profitability remains a challenge.  Sons of Gwalia's lack of readily available data makes a comprehensive analysis difficult, requiring more in-depth research."
                },
                {
                    "speaker": "0",
                    "text": "So, in summary, a cautious optimism for Grab, pending further analysis of their operational efficiency, and a need for more information on Sons of Gwalia.  How does this compare to your initial projections for both companies, and how are you adjusting your portfolio strategy accordingly?"
                }
            ],
            "key_companies": [
                {
                    "extracted_entity": "Grab Holdings",
                    "official_name": "Grab Holdings Limited",
                    "ticker": "GRAB"
                },
                {
                    "extracted_entity": "Sons of Gwalia",
                    "official_name": "Sons of Gwalia",
                    "ticker": ""
                }
            ]
        }
    ]
}